jlv/__init__.py
jlv/jlv.py
jlv/test.py
jlv-0.0.2.dist-info/METADATA
jlv-0.0.2.dist-info/RECORD
jlv-0.0.2.dist-info/WHEEL
jlv-0.0.2.dist-info/entry_points.txt
jlv-0.0.2.dist-info/top_level.txt
