Metadata-Version: 2.1
Name: jlv
Version: 0.0.2
Summary: A simple command line journal tool
Home-page: https://github.com/stelabr/jlv
Author: Stel Drake
Author-email: stelabr2@gmail.com
License: UNKNOWN
Platform: UNKNOWN
Classifier: Programming Language :: Python :: 3
Classifier: License :: OSI Approved :: MIT License
Classifier: Operating System :: OS Independent
